dchelp/__init__.py
dchelp/cli.py
dchelp/image.py
oktacmd/__init__.py
oktacmd/__main__.py
oktacmd/cli.py
oktacmd/common.py
oktacmd/main.py
oktacmd/okta.py
dc_help-0.0.2.dist-info/LICENSE
dc_help-0.0.2.dist-info/METADATA
dc_help-0.0.2.dist-info/WHEEL
dc_help-0.0.2.dist-info/entry_points.txt
dc_help-0.0.2.dist-info/top_level.txt
dc_help-0.0.2.dist-info/RECORD
