Metadata-Version: 2.1
Name: dc-help
Version: 0.0.2
Summary: docker-compose helper
Home-page: https://github.com/perfectstorm88/dchelp
Author: perfectstorm88
Author-email: perfectstorm88@163.com
License: MIT Licence
Keywords: pip,docker-compose,cli,docker,helper
Platform: any
Requires-Python: >=2.7
